dnnocr/__init__.py
dnnocr/base.py
dnnocr/libgcc_s_seh-1.dll
dnnocr/libgfortran-3.dll
dnnocr/libocr.so
dnnocr/libopenblas.dll
dnnocr/libquadmath-0.dll
dnnocr/net.py
dnnocr/ocr.dll
dnnocr/model-chars/__init__.py
dnnocr/model-chars/deploy.prototxt
dnnocr/model-chars/label.txt
dnnocr/model-chars/mean_values.txt
dnnocr/model-chars/model.caffemodel
dnnocr-0.2.3.dist-info/METADATA
dnnocr-0.2.3.dist-info/RECORD
dnnocr-0.2.3.dist-info/WHEEL
dnnocr-0.2.3.dist-info/top_level.txt
