Metadata-Version: 2.1
Name: dnnocr
Version: 0.2.3
Summary: DnnOCR
Requires-Dist: numpy
